galacteek/__init__.py
galacteek/__version__.py
galacteek/appsettings.py
galacteek/guientrypoint.py
galacteek/pypicheck.py
galacteek/application/__init__.py
galacteek/application/config.yaml
galacteek/blockchain/__init__.py
galacteek/blockchain/ethereum/__init__.py
galacteek/blockchain/ethereum/account.py
galacteek/blockchain/ethereum/contract.py
galacteek/blockchain/ethereum/ctrl.py
galacteek/blockchain/ethereum/infura/__init__.py
galacteek/blockchain/ethereum/infura/endpoints.py
galacteek/browser/__init__.py
galacteek/browser/interceptor.py
galacteek/browser/pslisteners.py
galacteek/browser/webproxy.py
galacteek/browser/schemes/__init__.py
galacteek/browser/schemes/config.yaml
galacteek/browser/schemes/ipid.py
galacteek/browser/web3channels/__init__.py
galacteek/browser/webprofiles/__init__.py
galacteek/browser/webprofiles/config.yaml
galacteek/config/__init__.py
galacteek/config/table.py
galacteek/config/util.py
galacteek/config/cmods/__init__.py
galacteek/config/cmods/pinning.py
galacteek/config/defaults/__init__.py
galacteek/config/defaults/config-default.yaml
galacteek/core/__init__.py
galacteek/core/analyzer.py
galacteek/core/aservice.py
galacteek/core/asynccache.py
galacteek/core/asynclib.py
galacteek/core/captcha.py
galacteek/core/chattokens.py
galacteek/core/clipboard.py
galacteek/core/countries.py
galacteek/core/db.py
galacteek/core/fswatcher.py
galacteek/core/glogger.py
galacteek/core/ipfsmarks.py
galacteek/core/iphandle.py
galacteek/core/iptags.py
galacteek/core/jsono.py
galacteek/core/jtraverse.py
galacteek/core/message.py
galacteek/core/modelhelpers.py
galacteek/core/multihashmetadb.py
galacteek/core/objects.py
galacteek/core/orbitdb.py
galacteek/core/orbitdbcfg.py
galacteek/core/pkglister.py
galacteek/core/process.py
galacteek/core/ps.py
galacteek/core/signaltowers.py
galacteek/core/softident.py
galacteek/core/tmpf.py
galacteek/core/userdag.py
galacteek/core/ctx/__init__.py
galacteek/core/ctx/config.yaml
galacteek/core/edags/__init__.py
galacteek-0.5.0.dist-info/AUTHORS.rst
galacteek-0.5.0.dist-info/LICENSE
galacteek-0.5.0.dist-info/LICENSE.Qt.GPLv3
galacteek-0.5.0.dist-info/LICENSE.go-ipfs
galacteek-0.5.0.dist-info/METADATA
galacteek-0.5.0.dist-info/WHEEL
galacteek-0.5.0.dist-info/entry_points.txt
galacteek-0.5.0.dist-info/top_level.txt
galacteek-0.5.0.dist-info/RECORD
