Metadata-Version: 2.1
Name: galacteek
Version: 0.5.0
Summary: Browser for the distributed web
Home-page: https://github.com/pinnaculum/galacteek
Author: cipres
Author-email: galacteek@protonmail.com
License: GPL3
Keywords: asyncio,aiohttp,ipfs
Platform: UNKNOWN
Classifier: Environment :: X11 Applications :: Qt
Classifier: Framework :: AsyncIO
Classifier: Topic :: Desktop Environment :: File Managers
Classifier: Topic :: Internet :: WWW/HTTP :: Browsers
Classifier: Development Status :: 4 - Beta
Classifier: Natural Language :: English
Classifier: Operating System :: OS Independent
Classifier: License :: OSI Approved :: GNU General Public License v3 (GPLv3)
Classifier: Topic :: System :: Filesystems
Classifier: Programming Language :: Python
Classifier: Programming Language :: Python :: 3.6
Classifier: Programming Language :: Python :: 3.7
Classifier: Programming Language :: Python :: 3.8
Classifier: Programming Language :: Python :: 3.9
Requires-Dist: aiodns (>=2.0.0)
Requires-Dist: aiofiles (>=0.4.0)
Requires-Dist: aiohttp (>=3.7.4)
Requires-Dist: aiohttp-socks (>=0.5.5)
Requires-Dist: aioipfs (>=0.5.5)
Requires-Dist: aiojobs (>=0.2.2)
Requires-Dist: aiopubsub (==2.1.5)
Requires-Dist: aiorwlock (>=0.6.0)
Requires-Dist: aiosqlite (<0.17.0,>=0.16.0)
Requires-Dist: async-generator (>=1.10)
Requires-Dist: async-timeout (>=3.0.1)
Requires-Dist: asyncio-extras (>=1.3.2)
Requires-Dist: asyncio-throttle (>=1.0.1)
Requires-Dist: asyncqt (==0.8.0)
Requires-Dist: attr (>=0.3.1)
Requires-Dist: base58 (<2.0,>=1.0.2)
Requires-Dist: bencodepy (>=0.9.5)
Requires-Dist: bitarray (>=1.6.1)
Requires-Dist: cachetools (>=3.1.1)
Requires-Dist: claptcha (>=0.3.3)
Requires-Dist: colour (==0.1.5)
Requires-Dist: feedgen (==0.9.0)
Requires-Dist: feedparser (>=5.2.0)
Requires-Dist: filelock (>=3.0.1)
Requires-Dist: gitpython (>=2.1.11)
Requires-Dist: jinja2 (>=2.10.1)
Requires-Dist: json-traverse (>=0.4)
Requires-Dist: jsonschema (<4.0.0,>=3.0.0)
Requires-Dist: jwcrypto (>=0.8)
Requires-Dist: logbook (>=1.5.3)
Requires-Dist: markdown (>=3.0)
Requires-Dist: memory-profiler (>=0.58.0)
Requires-Dist: mkdocs (>=1.1.2)
Requires-Dist: mkdocs-bootswatch (>=1.1)
Requires-Dist: mode (==4.4.0)
Requires-Dist: multiaddr (>=0.0.8)
Requires-Dist: omegaconf (==2.0.5)
Requires-Dist: orjson (<3.4,>=3)
Requires-Dist: pillow (>=6.0.0)
Requires-Dist: protobuf (==3.6.1)
Requires-Dist: psutil (>=5.7.2)
Requires-Dist: pydot (>=1.4.2)
Requires-Dist: py-multicodec (==0.2.1)
Requires-Dist: py-multihash (>=0.2.3)
Requires-Dist: pycryptodomex (==3.9.8)
Requires-Dist: pygments (>=2.3.1)
Requires-Dist: pyld (>=2.0.2)
Requires-Dist: PyNaCl (>=1.4.0)
Requires-Dist: python-magic (>=0.4.15)
Requires-Dist: python3-crdt (>=1.0.3)
Requires-Dist: py-multibase (>=1.0.3)
Requires-Dist: pyyaml (>=5.3.1)
Requires-Dist: pyzbar (>=0.1.8)
Requires-Dist: qrcode (==6.1)
Requires-Dist: qtawesome (>=0.7.2)
Requires-Dist: random-username (>=1.0.2)
Requires-Dist: rule-engine (>=2.1.0)
Requires-Dist: strict-rfc3339 (>=0.7)
Requires-Dist: tortoise-orm (>=0.16.21)
Requires-Dist: validators (>=0.18.1)
Requires-Dist: yarl (==1.5.1)
Provides-Extra: docs
Requires-Dist: sphinx (==1.8.5) ; extra == 'docs'
Provides-Extra: markdown-extensions
Requires-Dist: mdx-unimoji (>=1.0) ; extra == 'markdown-extensions'
Requires-Dist: mkdocs-blog-plugin (>=0.25) ; extra == 'markdown-extensions'
Provides-Extra: ui-pyqt-5.13
Requires-Dist: pyqt5 (==5.13.2) ; extra == 'ui-pyqt-5.13'
Requires-Dist: pyqtchart (==5.13.1) ; extra == 'ui-pyqt-5.13'
Requires-Dist: pyqtwebengine (==5.13.2) ; extra == 'ui-pyqt-5.13'
Provides-Extra: ui-pyqt-5.15
Requires-Dist: pyqt5 (>=5.15.2) ; extra == 'ui-pyqt-5.15'
Requires-Dist: pyqtchart (>=5.15.2) ; extra == 'ui-pyqt-5.15'
Requires-Dist: pyqtwebengine (>=5.15.2) ; extra == 'ui-pyqt-5.15'
